micro_traffic_sim/__init__.py
micro_traffic_sim/cell_pb2.py
micro_traffic_sim/cell_pb2.pyi
micro_traffic_sim/cell_pb2_grpc.py
micro_traffic_sim/conflict_zones_pb2.py
micro_traffic_sim/conflict_zones_pb2.pyi
micro_traffic_sim/conflict_zones_pb2_grpc.py
micro_traffic_sim/py.typed
micro_traffic_sim/service_pb2.py
micro_traffic_sim/service_pb2.pyi
micro_traffic_sim/service_pb2_grpc.py
micro_traffic_sim/session_pb2.py
micro_traffic_sim/session_pb2.pyi
micro_traffic_sim/session_pb2_grpc.py
micro_traffic_sim/step_pb2.py
micro_traffic_sim/step_pb2.pyi
micro_traffic_sim/step_pb2_grpc.py
micro_traffic_sim/tls_pb2.py
micro_traffic_sim/tls_pb2.pyi
micro_traffic_sim/tls_pb2_grpc.py
micro_traffic_sim/trip_pb2.py
micro_traffic_sim/trip_pb2.pyi
micro_traffic_sim/trip_pb2_grpc.py
micro_traffic_sim/uuid_pb2.py
micro_traffic_sim/uuid_pb2.pyi
micro_traffic_sim/uuid_pb2_grpc.py
micro_traffic_sim-0.1.0.dist-info/METADATA
micro_traffic_sim-0.1.0.dist-info/WHEEL
micro_traffic_sim-0.1.0.dist-info/top_level.txt
micro_traffic_sim-0.1.0.dist-info/RECORD
