Metadata-Version: 2.4
Name: micro-traffic-sim
Version: 0.1.0
Summary: Python gRPC client for microscopic traffic simulation
Author-email: Dmitrii Lopanov <sexykdi@gmail.com>
License: Apache-2.0
Project-URL: Homepage, https://github.com/LdDl/micro_traffic_sim_grpc
Project-URL: Documentation, https://github.com/LdDl/micro_traffic_sim_grpc/tree/main/clients/python
Project-URL: Repository, https://github.com/LdDl/micro_traffic_sim_grpc
Project-URL: Issues, https://github.com/LdDl/micro_traffic_sim_grpc/issues
Keywords: traffic,simulation,grpc,cellular-automata,transportation
Classifier: Development Status :: 4 - Beta
Classifier: Intended Audience :: Developers
Classifier: Intended Audience :: Science/Research
Classifier: License :: OSI Approved :: Apache Software License
Classifier: Operating System :: OS Independent
Classifier: Programming Language :: Python :: 3
Classifier: Programming Language :: Python :: 3.10
Classifier: Programming Language :: Python :: 3.11
Classifier: Programming Language :: Python :: 3.12
Classifier: Programming Language :: Python :: 3.13
Classifier: Topic :: Scientific/Engineering
Classifier: Typing :: Typed
Requires-Python: >=3.10
Requires-Dist: grpcio>=1.60.0
Requires-Dist: protobuf>=4.25.0
Provides-Extra: dev
Requires-Dist: grpcio-tools>=1.60.0; extra == "dev"
